{"otherData": {},"traceEvents":[{},{"cat":"function","dur":26,"name":"__cdecl GameEngine::OpenGLTexture2D::~OpenGLTexture2D(void)","ph":"X","pid":0,"tid":3556,"ts":373065712704.900},{"cat":"function","dur":3,"name":"__cdecl GameEngine::OpenGLShader::~OpenGLShader(void)","ph":"X","pid":0,"tid":3556,"ts":373065712876.900},{"cat":"function","dur":4,"name":"__cdecl GameEngine::OpenGLVertexArray::~OpenGLVertexArray(void)","ph":"X","pid":0,"tid":3556,"ts":373065712949.300},{"cat":"function","dur":50,"name":"__cdecl GameEngine::OpenGLIndexBuffer::~OpenGLIndexBuffer(void)","ph":"X","pid":0,"tid":3556,"ts":373065713020.900},{"cat":"function","dur":3,"name":"__cdecl GameEngine::OpenGLVertexBuffer::~OpenGLVertexBuffer(void)","ph":"X","pid":0,"tid":3556,"ts":373065713151.700},{"cat":"function","dur":517,"name":"void __cdecl GameEngine::Renderer2D::ShutDown(void)","ph":"X","pid":0,"tid":3556,"ts":373065712703.200},{"cat":"function","dur":579,"name":"__cdecl GameEngine::Application::~Application(void)","ph":"X","pid":0,"tid":3556,"ts":373065712702.500},{"cat":"function","dur":0,"name":"void __cdecl Sandbox2D::OnDetach(void)","ph":"X","pid":0,"tid":3556,"ts":373065713341.200},{"cat":"function","dur":9,"name":"__cdecl GameEngine::OpenGLTexture2D::~OpenGLTexture2D(void)","ph":"X","pid":0,"tid":3556,"ts":373065713400.200},{"cat":"function","dur":1500,"name":"void __cdecl GameEngine::ImGuiLayer::OnDetach(void)","ph":"X","pid":0,"tid":3556,"ts":373065713474.400},{"cat":"function","dur":29927,"name":"void __cdecl GameEngine::WindowsWindow::Shutdown(void)","ph":"X","pid":0,"tid":3556,"ts":373065715086.600},{"cat":"function","dur":30142,"name":"__cdecl GameEngine::WindowsWindow::~WindowsWindow(void)","ph":"X","pid":0,"tid":3556,"ts":373065715086.200}]}